opensecureconf_client.py
opensecureconf_client-2.3.0.dist-info/licenses/LICENSE
opensecureconf_client-2.3.0.dist-info/METADATA
opensecureconf_client-2.3.0.dist-info/WHEEL
opensecureconf_client-2.3.0.dist-info/top_level.txt
opensecureconf_client-2.3.0.dist-info/RECORD
