Metadata-Version: 2.4
Name: opensecureconf-client
Version: 2.3.0
Summary: Python client library for OpenSecureConf encrypted configuration management API with clustering support
Author-email: Alessandro Pioli <alessandro.pioli+apioli-pypi@gmail.com>
Maintainer-email: Alessandro Pioli <alessandro.pioli+apioli-pypi@gmail.com>
License: MIT
Project-URL: Homepage, https://github.com/lordraw77/OpenSecureConf
Project-URL: Documentation, https://github.com/lordraw77/OpenSecureConf/blob/main/client/README.md
Project-URL: Repository, https://github.com/lordraw77/OpenSecureConf/tree/main/client
Project-URL: Issues, https://github.com/lordraw77/OpenSecureConf/issues
Keywords: configuration,encryption,api-client,secure,config-management,clustering,distributed-config,secrets-management
Classifier: Development Status :: 4 - Beta
Classifier: Intended Audience :: Developers
Classifier: License :: OSI Approved :: MIT License
Classifier: Programming Language :: Python :: 3
Classifier: Programming Language :: Python :: 3.8
Classifier: Programming Language :: Python :: 3.9
Classifier: Programming Language :: Python :: 3.10
Classifier: Programming Language :: Python :: 3.11
Classifier: Programming Language :: Python :: 3.12
Classifier: Programming Language :: Python :: 3.13
Classifier: Topic :: Software Development :: Libraries :: Python Modules
Classifier: Topic :: Security :: Cryptography
Classifier: Topic :: System :: Distributed Computing
Requires-Python: >=3.8
License-File: LICENSE
Requires-Dist: requests>=2.28.0
Requires-Dist: urllib3>=1.26.0
Provides-Extra: dev
Requires-Dist: pytest>=7.0.0; extra == "dev"
Requires-Dist: pytest-cov>=4.0.0; extra == "dev"
Requires-Dist: black>=23.0.0; extra == "dev"
Requires-Dist: flake8>=6.0.0; extra == "dev"
Requires-Dist: mypy>=1.0.0; extra == "dev"
Requires-Dist: pylint>=2.17.0; extra == "dev"
Requires-Dist: isort>=5.12.0; extra == "dev"
Provides-Extra: enhanced
Requires-Dist: urllib3>=2.0.0; extra == "enhanced"
Dynamic: license-file
